warema_wms/__init__.py
warema_wms/shade.py
warema_wms/wms_controller.py
warema_wms_controller-0.2.4.dist-info/LICENSE
warema_wms_controller-0.2.4.dist-info/METADATA
warema_wms_controller-0.2.4.dist-info/WHEEL
warema_wms_controller-0.2.4.dist-info/top_level.txt
warema_wms_controller-0.2.4.dist-info/RECORD
