Metadata-Version: 2.1
Name: warema-wms-controller
Version: 0.2.4
Summary: A library to control a Warema WMS WebControl web server.
Home-page: https://github.com/cornim/wms_webcontrol.git
Author: Dr. Cornelius Mund
Author-email: cornelius.mund@gmail.com
Classifier: Programming Language :: Python :: 3
Classifier: License :: OSI Approved :: GNU Lesser General Public License v3 (LGPLv3)
Classifier: Operating System :: OS Independent
License-File: LICENSE
Requires-Dist: requests
